finlearner/__init__.py
finlearner/anomaly.py
finlearner/data.py
finlearner/ml_models.py
finlearner/models.py
finlearner/options.py
finlearner/pinn.py
finlearner/plotting.py
finlearner/portfolio.py
finlearner/risk.py
finlearner/technical.py
finlearner/utils.py
finlearner-0.1.1.dist-info/licenses/LICENSE
finlearner-0.1.1.dist-info/METADATA
finlearner-0.1.1.dist-info/WHEEL
finlearner-0.1.1.dist-info/top_level.txt
finlearner-0.1.1.dist-info/RECORD
