Metadata-Version: 2.4
Name: finlearner
Version: 0.1.1
Summary: State-of-the-art Financial Analysis & Deep Learning Library
Author-email: Ankit Dutta <ankitdutta428@gmail.com>
Maintainer-email: Ankit Dutta <ankitdutta428@gmail.com>
License: Apache-2.0
Project-URL: Homepage, https://github.com/ankitdutta428/finlearner
Project-URL: Documentation, https://github.com/ankitdutta428/finlearner#readme
Project-URL: Repository, https://github.com/ankitdutta428/finlearner.git
Project-URL: Issues, https://github.com/ankitdutta428/finlearner/issues
Keywords: finance,machine-learning,deep-learning,stock-market,portfolio-optimization,technical-analysis,lstm,time-series,options-pricing,black-scholes
Classifier: Development Status :: 4 - Beta
Classifier: Intended Audience :: Developers
Classifier: Intended Audience :: Financial and Insurance Industry
Classifier: Intended Audience :: Science/Research
Classifier: License :: OSI Approved :: Apache Software License
Classifier: Operating System :: OS Independent
Classifier: Programming Language :: Python :: 3
Classifier: Programming Language :: Python :: 3.8
Classifier: Programming Language :: Python :: 3.9
Classifier: Programming Language :: Python :: 3.10
Classifier: Programming Language :: Python :: 3.11
Classifier: Programming Language :: Python :: 3.12
Classifier: Topic :: Office/Business :: Financial :: Investment
Classifier: Topic :: Scientific/Engineering :: Artificial Intelligence
Requires-Python: >=3.8
License-File: LICENSE
Requires-Dist: numpy>=1.21.0
Requires-Dist: pandas>=1.3.0
Requires-Dist: yfinance>=0.2.0
Requires-Dist: plotly>=5.0.0
Requires-Dist: matplotlib>=3.5.0
Requires-Dist: seaborn>=0.11.0
Requires-Dist: scipy>=1.7.0
Requires-Dist: scikit-learn>=1.0.0
Requires-Dist: tensorflow>=2.10.0
Provides-Extra: dev
Requires-Dist: pytest>=7.0.0; extra == "dev"
Requires-Dist: pytest-cov>=4.0.0; extra == "dev"
Dynamic: license-file
